qase/robotframework/__init__.py
qase/robotframework/filter.py
qase/robotframework/listener.py
qase/robotframework/method.py
qase/robotframework/models.py
qase/robotframework/plugin.py
qase/robotframework/tag_parser.py
qase/robotframework/types.py
qase_robotframework-5.0.0.dist-info/licenses/LICENSE
qase_robotframework-5.0.0.dist-info/METADATA
qase_robotframework-5.0.0.dist-info/WHEEL
qase_robotframework-5.0.0.dist-info/top_level.txt
qase_robotframework-5.0.0.dist-info/RECORD
