Metadata-Version: 2.4
Name: qase-robotframework
Version: 5.0.0
Summary: Qase Robot Framework Plugin
Author-email: Qase Team <support@qase.io>
License:                                  Apache License
Project-URL: Homepage, https://github.com/qase-tms/qase-python/tree/main/qase-robotframework
Classifier: Development Status :: 5 - Production/Stable
Classifier: Framework :: Robot Framework
Classifier: Programming Language :: Python
Classifier: Programming Language :: Python :: 3
Classifier: Programming Language :: Python :: 3 :: Only
Classifier: Programming Language :: Python :: 3.9
Classifier: Programming Language :: Python :: 3.10
Classifier: Programming Language :: Python :: 3.11
Classifier: Programming Language :: Python :: 3.12
Classifier: Programming Language :: Python :: 3.13
Requires-Python: >=3.9
License-File: LICENSE
Requires-Dist: qase-python-commons~=5.0.0
Requires-Dist: filelock>=3.12.2
Provides-Extra: testing
Requires-Dist: pytest; extra == "testing"
Requires-Dist: pytest-cov; extra == "testing"
Dynamic: license-file
